pymodaq_plugins_KDC101/__init__.py
pymodaq_plugins_KDC101/utils.py
pymodaq_plugins_KDC101/__pycache__/__init__.cpython-38.pyc
pymodaq_plugins_KDC101/__pycache__/utils.cpython-38.pyc
pymodaq_plugins_KDC101/daq_move_plugins/__init__.py
pymodaq_plugins_KDC101/daq_move_plugins/daq_move_KDC101.py
pymodaq_plugins_KDC101/daq_viewer_plugins/__init__.py
pymodaq_plugins_KDC101/hardware/__init__.py
pymodaq_plugins_KDC101/hardware/kinesis.py
pymodaq_plugins_KDC101/hardware/__pycache__/__init__.cpython-38.pyc
pymodaq_plugins_KDC101/hardware/__pycache__/kinesis.cpython-38.pyc
pymodaq_plugins_KDC101/resources/VERSION
pymodaq_plugins_KDC101/resources/__init__.py
pymodaq_plugins_KDC101/resources/config_template.toml
pymodaq_plugins_KDC101-1.4.1.dist-info/LICENSE
pymodaq_plugins_KDC101-1.4.1.dist-info/METADATA
pymodaq_plugins_KDC101-1.4.1.dist-info/WHEEL
pymodaq_plugins_KDC101-1.4.1.dist-info/entry_points.txt
pymodaq_plugins_KDC101-1.4.1.dist-info/top_level.txt
pymodaq_plugins_KDC101-1.4.1.dist-info/RECORD
